{
  "slug": "background",
  "emoji": "🎧",
  "title": "Под дела",
  "lang": "ru",
  "updated_at": "2026-07-17T17:13:48Z",
  "items": [
    {
      "id": 34549,
      "media_type": "tv",
      "title": "Великий пекарь Британии",
      "original_title": "The Great British Bake Off",
      "overview": "Британское телевизионное кулинарное соревнование по выпечке, в котором среди участников выбирают лучшего пекаря-любителя. Считается, что шоу вновь пробудило интерес к выпечке по всей Великобритании, а многие его участники, включая победителей, впоследствии построили карьеру, связанную с кондитерским и пекарским делом.",
      "poster_path": "/bNa02AorKSBRfWfVPmsL7SJrdfs.jpg",
      "backdrop_path": "/7rB1VhVXtLFTnOCY1Hz7ZEIz7CO.jpg",
      "genre_ids": [
        10764
      ],
      "vote_average": 7.5,
      "vote_count": 101,
      "release_date": "2010-08-17"
    },
    {
      "id": 32726,
      "media_type": "tv",
      "title": "Закусочная Боба",
      "original_title": "Bob's Burgers",
      "overview": "Главный персонаж сериала — Боб. Он владеет небольшой закусочной, где продают гамбургеры. Боб занимается бизнесом со своей семьёй. Помогают ему жена-истеричка и трое детей, которые больше мешают процветанию дела Боба.",
      "poster_path": "/brZYpomaBk91PPzl87U2UGkDSEA.jpg",
      "backdrop_path": "/rUABoTPO0OLq2wlHiFWezxpV6fo.jpg",
      "genre_ids": [
        16,
        35
      ],
      "vote_average": 7.841,
      "vote_count": 1100,
      "release_date": "2011-01-09"
    },
    {
      "id": 35058,
      "media_type": "tv",
      "title": "Property Brothers",
      "original_title": "Property Brothers",
      "overview": "",
      "poster_path": "/ccggWzKxSao1VNaVFJNLkZG96Fb.jpg",
      "backdrop_path": "/4yE7q1MwvM4JLlBH9WcmP2GY26l.jpg",
      "genre_ids": [
        10764
      ],
      "vote_average": 7.7,
      "vote_count": 98,
      "release_date": "2011-01-04"
    },
    {
      "id": 12786,
      "media_type": "tv",
      "title": "Расследования Мёрдока",
      "original_title": "Murdoch Mysteries",
      "overview": "Конец XIX-го века. На улицах Торонто происходят странные убийства. Детектив Уильям Мёрдок раскрывает их с помощью новой науки - криминалистики. У него есть союзник - судебный врач Джулия Огден. Ни юный возраст, ни хорошее воспитание, ни пышные юбки не мешают ей вскрывать трупы и проводить экспертизы.",
      "poster_path": "/fQGrNZbSTcIghYMz4IdhP45d4tl.jpg",
      "backdrop_path": "/hYmHyUlJMQgeazELoHnORrEQ0vE.jpg",
      "genre_ids": [
        9648,
        18
      ],
      "vote_average": 7.7,
      "vote_count": 291,
      "release_date": "2008-01-24"
    },
    {
      "id": 2996,
      "media_type": "tv",
      "title": "Офис",
      "original_title": "The Office",
      "overview": "Действие сериала разворачивается в региональном офисе компании, торгующей бумагой. Зрителю предлагается посмотреть на жизнь офисных работников изнутри, в стиле реалити-шоу - события и происшествия комментируются их участниками.",
      "poster_path": "/lJro4HDtF8EjZZQlknSYeP7g1js.jpg",
      "backdrop_path": "/9GWU1AyNqUYIUl1tU7CvXEHUVs9.jpg",
      "genre_ids": [
        35
      ],
      "vote_average": 7.8,
      "vote_count": 965,
      "release_date": "2001-07-09"
    },
    {
      "id": 764,
      "media_type": "tv",
      "title": "Чисто английские убийства",
      "original_title": "Midsomer Murders",
      "overview": "Чисто английский сериал по чисто английским романам Каролины Грэм. От перемены мест слагаемых сумма английского детектива не меняется, и время не властно над истинными ценностями. Чопорные островитяне по-прежнему совершают самые изощренные преступления, за ними с самым обстоятельным и почтительным видом следуют элегантные сыщики, а фоном для этих сдержанных страстей остаются зеленые лужайки и тенистые аллеи, сумрачные кабинеты и холодные спальни. Почти все действие происходит в деревнях небольшого, образцово безмятежного графства Мидсомер. Иной раз на этом пасторальном фоне происходит такое, чего и в столицах не видывали. А службу, которая опасна и трудна, деревенские полицейские не выбирают.",
      "poster_path": "/8dCDCmvNgRdihysgZNAzMRJC9gM.jpg",
      "backdrop_path": "/qVmgq1KXBp6BF2EqYPPaUG9iUGy.jpg",
      "genre_ids": [
        80,
        18,
        9648
      ],
      "vote_average": 7.469,
      "vote_count": 360,
      "release_date": "1997-03-23"
    },
    {
      "id": 68106,
      "media_type": "tv",
      "title": "Kim's Convenience",
      "original_title": "Kim's Convenience",
      "overview": "",
      "poster_path": "/82Vue6MPuYZzlpggR65cvWdBdy.jpg",
      "backdrop_path": "/oh5ZkLhrrt1EmGfRZ4qqm743X6b.jpg",
      "genre_ids": [
        35
      ],
      "vote_average": 7.657,
      "vote_count": 175,
      "release_date": "2016-10-11"
    },
    {
      "id": 1831,
      "media_type": "tv",
      "title": "Истории дизайна",
      "original_title": "Grand Designs",
      "overview": "Передача о дизайне, архитектуре, строительстве. Кевин МакКлауд, ведущий программы, помогает участникам, например, проектирует ландшафтный дизайн. Кевин следит за стройкой от начала до конца, комментирует процесс и высказывает своё окончательное мнение о проекте.",
      "poster_path": "/4UiJCgR77N7cd8eJ4tolxhs8fGX.jpg",
      "backdrop_path": "/vMH57KXBgkASnpEJOv4fyzJKrQj.jpg",
      "genre_ids": [
        99
      ],
      "vote_average": 7.1,
      "vote_count": 55,
      "release_date": "1999-04-29"
    },
    {
      "id": 48891,
      "media_type": "tv",
      "title": "Бруклин 9-9",
      "original_title": "Brooklyn Nine-Nine",
      "overview": "История о том, что происходит, когда у детектива, не воспринимающего ничего серьезно, появляется новый руководитель, который хочет, чтобы он рос и с уважением относился к своей должности.",
      "poster_path": "/77mEUuM28cSV8YSn4EcF3koRHHT.jpg",
      "backdrop_path": "/9AeiA1XtP5sel2tAf9LaGeUjhDb.jpg",
      "genre_ids": [
        35,
        80
      ],
      "vote_average": 8.211,
      "vote_count": 4026,
      "release_date": "2013-09-17"
    },
    {
      "id": 8592,
      "media_type": "tv",
      "title": "Парки и зоны отдыха",
      "original_title": "Parks and Recreation",
      "overview": "Простой чиновник Лесли Ноуп однажды поняла, что своей работой не приносит обществу никакой пользы. Тогда же она решает превратить заброшенный карьер практически в парк культуры и отдыха. Препятствием на её пути, конечно же, станут негибкая бюрократическая система, эгоистичные соседи, не желающие перемен даже к лучшему, и фирмы-застройщики, сразу заинтересовавшиеся ненужным им до этого бесхозным участком. Но Лесли им не уступит...",
      "poster_path": "/95ilzv0DIxYfu6ahbxkYhm4pk2I.jpg",
      "backdrop_path": "/frwl2zBNAl5ZbFDJGoJv0mYo0rF.jpg",
      "genre_ids": [
        35
      ],
      "vote_average": 8.043,
      "vote_count": 1854,
      "release_date": "2009-04-09"
    }
  ]
}