{
  "slug": "cozy-rain",
  "icon": "<svg viewBox=\"0 0 512 512\" xmlns=\"http://www.w3.org/2000/svg\"><rect x=\"104\" y=\"176\" width=\"216\" height=\"208\" rx=\"28\" fill=\"currentColor\"/><path fill=\"none\" stroke=\"currentColor\" stroke-width=\"28\" d=\"M320 224h28a52 52 0 0 1 0 104h-28\"/><path fill=\"none\" stroke=\"currentColor\" stroke-width=\"20\" stroke-linecap=\"round\" d=\"M168 92c-18 22 18 40 0 60M248 92c-18 22 18 40 0 60\"/></svg>",
  "title": "Затишок",
  "lang": "uk",
  "updated_at": "2026-07-21T23:03:40Z",
  "items": [
    {
      "id": 416477,
      "media_type": "movie",
      "title": "Кохання – хвороба",
      "original_title": "The Big Sick",
      "overview": "У міру розвитку стосунків закоханій парі доводиться зіткнутися зі своїми культурними відмінностями.",
      "poster_path": "/9fJTT8pBxxQsFILJHTtHhdYFr77.jpg",
      "backdrop_path": "/fYI8WX2DquAHMqwh5mOMxc6RU5j.jpg",
      "genre_ids": [
        35,
        18,
        10749
      ],
      "vote_average": 7.323,
      "vote_count": 2655,
      "release_date": "2017-03-30"
    },
    {
      "id": 167073,
      "media_type": "movie",
      "title": "Бруклін",
      "original_title": "Brooklyn",
      "overview": "Історія Елліс Лейсі, яка неохоче покидає своє рідне ірландське містечко і вирушає на пошуки роботи до Америки. Вона поселяється в Брукліні, поступово виліковується від ностальгії і починає насолоджуватися повітрям свободи. До всього іншого Елліс закохується, але трагічні новини з батьківщини змушують її повернутися до Ірландії, де вона зустрічає іншого чоловіка і в результаті змушена робити нелегкий вибір.",
      "poster_path": "/pagrbjTRzrQEZG6N15vtcq3UHGD.jpg",
      "backdrop_path": "/2T4bqHgYfzXNQoALJsvhW40kDTg.jpg",
      "genre_ids": [
        10749,
        18,
        36
      ],
      "vote_average": 7.297,
      "vote_count": 3286,
      "release_date": "2015-10-20"
    },
    {
      "id": 66573,
      "media_type": "tv",
      "title": "У кращому світі",
      "original_title": "The Good Place",
      "overview": "Навіжена Елеонор з Нью Джерсі потрапляє туди, де їй наочно пояснюють, що все своє життя вона була вкрай поганою людиною. Головній героїні належить навчитися відрізняти хороше від поганого і допомогти їй дорости до хорошої людини візьметься наставник на ім'я Майкл.",
      "poster_path": "/iZd6jJEzT7sszoFLd5XsYXgctfq.jpg",
      "backdrop_path": "/tZmlWeFEMvxrjJhBJJcLNXpSRiG.jpg",
      "genre_ids": [
        10765,
        35
      ],
      "vote_average": 7.97,
      "vote_count": 2003,
      "release_date": "2016-09-19"
    },
    {
      "id": 69798,
      "media_type": "movie",
      "title": "Переростки",
      "original_title": "The Inbetweeners Movie",
      "overview": "Втомившись від своїх проблем, четверо вісімнадцятирічних приятелів підлітків з півдня Англії відправляються на двотижневий відпочинок до Греції.",
      "poster_path": "/nNWPH4BZp3qsXgypnv9yyP0sVZy.jpg",
      "backdrop_path": "/ffAXhWIgVB9PRxzlDyrDKYckImx.jpg",
      "genre_ids": [
        35
      ],
      "vote_average": 6.19,
      "vote_count": 991,
      "release_date": "2011-08-19"
    },
    {
      "id": 232175,
      "media_type": "movie",
      "title": "Подаруй мені притулок",
      "original_title": "Gimme Shelter",
      "overview": "Головна героїня фільму, вагітна молода жінка, не в силах витримати нотацій матері, тому відправляється за допомогою до свого рідного батька. Ніколи раніше не спілкуючись зі своєю дочкою, її батько спочатку наполягає на аборті, але через деякий час у нього прокидаються батьківські почуття.",
      "poster_path": "/g692DI6d2aanTjSdPEPotk8h3PF.jpg",
      "backdrop_path": "/hTUveXKSPA7jWZ08MaXaHSvY6lO.jpg",
      "genre_ids": [
        18
      ],
      "vote_average": 6.582,
      "vote_count": 256,
      "release_date": "2013-10-17"
    },
    {
      "id": 283552,
      "media_type": "movie",
      "title": "Світло між двох океанів",
      "original_title": "The Light Between Oceans",
      "overview": "Історія розгортається на віддаленому від великої суші австралійському острові після закінчення Першої світової війни. Доглядач маяка і його дружина стикаються з моральною дилемою, коли знаходять в човні новонароджену дитину і мертвого чоловіка. Пара вирішує виховати дитину як свою власну, не уявляючи, наскільки руйнівними будуть наслідки їхнього вибору.",
      "poster_path": "/qreyKsnwYjh6yzYNDDLRIP0eJbM.jpg",
      "backdrop_path": "/s72jkxT7xPbfGxnE1lETq5OywvY.jpg",
      "genre_ids": [
        18,
        10749
      ],
      "vote_average": 7.066,
      "vote_count": 1432,
      "release_date": "2016-09-02"
    },
    {
      "id": 4538,
      "media_type": "movie",
      "title": "Поїзд до Дарджилінґа",
      "original_title": "The Darjeeling Limited",
      "overview": "Три придуркуваті братики, які не розмовляли один з одним цілий рік після смерті батька, опиняються в потязі, що їде через Індію. Тут вони з'явилися, послухавши заклик старшого з братів возз'єднатися в подорожі, яка повинна допомогти їм зрозуміти і пізнати себе, відновивши сімейні пута, що послабшали. Втім, незабаром це благе дійство сходить з потрібного курсу: недовірливі родичі починають лаятися і битися, внаслідок чого виявляються висадженими посеред пустелі. І, звичайно, це далеко не усі неприємності, які чекають на них.",
      "poster_path": "/hnA9g4ix1afSSgz49RUGL67jhRv.jpg",
      "backdrop_path": "/hKJ513GbmTSmTXJU1uCXclh5Wkh.jpg",
      "genre_ids": [
        12,
        18,
        35
      ],
      "vote_average": 7.144,
      "vote_count": 4010,
      "release_date": "2007-09-07"
    },
    {
      "id": 120467,
      "media_type": "movie",
      "title": "Готель «Ґранд Будапешт»",
      "original_title": "The Grand Budapest Hotel",
      "overview": "Картина розповість про легендарного конс'єржа популярного європейського готелю і простежить за його життям між двома світовими війнами, а також за його дружбою з юною співробітницею, яка стає його протеже.  Сюжет включає в себе крадіжку безцінної картини епохи Відродження, боротьбу за величезний спадок і потрясіння, що спіткали Європу під час першої половини XX століття...",
      "poster_path": "/u0bKng2BVQe7IOaJqoHwxnDx679.jpg",
      "backdrop_path": "/9udCLTxTFl28RxnK8Q05E154ZGa.jpg",
      "genre_ids": [
        35,
        18
      ],
      "vote_average": 8.026,
      "vote_count": 16232,
      "release_date": "2014-02-26"
    },
    {
      "id": 12837,
      "media_type": "movie",
      "title": "Таємне життя бджіл",
      "original_title": "The Secret Life of Bees",
      "overview": "1964 рік. Лілі Оуенс втратила мати й, будучи не в силах жити з батьком, збігає з будинку разом зі своєю єдиною подругою - Розалін - у містечко в Південній Кароліні. Розалін відома таємниця матері дівчинки, але сама Лілі поки про це не знає. На новому місці втікачки обґрунтовуються в трьох ексцентричних сестер, Аугуст, Мей і Джун...",
      "poster_path": "/b2exauTay5qtn7iOuJcRzLu1GMP.jpg",
      "backdrop_path": "/40K8NpPgBqIDukExvG4yWPkYEvO.jpg",
      "genre_ids": [
        10751,
        12,
        18
      ],
      "vote_average": 7.484,
      "vote_count": 585,
      "release_date": "2008-09-17"
    },
    {
      "id": 590,
      "media_type": "movie",
      "title": "Години",
      "original_title": "The Hours",
      "overview": "Картину умовно поділено на три частини, у кожній з них зображено один день із життя головних героїнь, долі яких химерно пов'язані між собою та майже ідентичні.\r 1923 рік. Героїня Ніколь Кідман — британська письменниця Вірджинія Вулф, яка почала писати свою нову книгу «Місіс Делловей».\r 1951 рік. Героїня Джуліан Мор — американська домогосподарка Лора Браун вагітна другою дитиною, живе у Лос-Анджелесі разом зі своїм чоловіком Деном і маленьким сином Річі.\r 2001 рік. Кларисса Воган, героїня Меріл Стріп, живе у Нью-Йорку і її день присвячений підготовці до вечірки з нагоди отримання важливої літературної премії Річардом Брауном — хворим на СНІД письменником, з яким вони зустрічалися ще в коледжі.",
      "poster_path": "/4myDtowDJQPQnkEDB1IWGtJR1Fo.jpg",
      "backdrop_path": "/3oHFSEr4TRnsyTxWGrmY8Xi2FrR.jpg",
      "genre_ids": [
        18
      ],
      "vote_average": 7.253,
      "vote_count": 1879,
      "release_date": "2002-12-27"
    },
    {
      "id": 1245,
      "media_type": "movie",
      "title": "Наприкінці дня",
      "original_title": "The Remains of the Day",
      "overview": "Стівенс - зразковий англійський дворецький, що все життя провів в старовинному маєтку. Він віддав своє серце служінню, і немає нічого, що змусило б його зрадити обов’язку. Несподівано звичний перебіг днів порушується, коли в маєтку з'являється нова економка міс Кентон. Стівенс намагається приховати глибокі почуття до цієї жінки, але ні вікова традиція, ні священні обов'язки не можуть зупинити кохання, що спалахнуло.",
      "poster_path": "/LbpROmw48NtjDfep2WfsZDJkBc.jpg",
      "backdrop_path": "/vFhxd3Z1zaV3Yu5XLpvWzSxJCe8.jpg",
      "genre_ids": [
        18,
        10749
      ],
      "vote_average": 7.359,
      "vote_count": 1522,
      "release_date": "1993-11-05"
    },
    {
      "id": 249688,
      "media_type": "movie",
      "title": "Кінець туру",
      "original_title": "The End of the Tour",
      "overview": "Незабаром після публікації роману \"Нескінченний жарт\" письменник Девід Фостер Уоллес вирушає в поїздку з журналістом Rolling Stones Девиідом Ліпскі, що готує про нього статтю. За п'ять днів між ними виник деякий довірчий зв'язок, що дозволив кожному з них поділитися своїми сокровенними думками і бажаннями. Так або інакше, інтерв'ю ніколи не було опубліковане - аудіокасети відправилися в шафу Ліпскі, а самі герої так більше і не зустрілись.",
      "poster_path": "/bWFdAcfUpWefaWSpw9QXjFO4Vfl.jpg",
      "backdrop_path": "/jfesUBA5dUxlPw2E1M7fCahTHG8.jpg",
      "genre_ids": [
        18
      ],
      "vote_average": 7.005,
      "vote_count": 614,
      "release_date": "2015-07-31"
    },
    {
      "id": 97367,
      "media_type": "movie",
      "title": "Місце під соснами",
      "original_title": "The Place Beyond the Pines",
      "overview": "Люк - професійний гонщик і працює в одному з небезпечних атракціонів містечка Скенектаді. Коли хлопець випадково дізнається, що у нього є новонароджений син, він вирішує допомогти своїй колишній дівчині з фінансами. Для цього він вирішує грабувати банки. Але на його шляху стає поліцейський Евері Кросс.",
      "poster_path": "/33jX6hyoYE9SFxZ5ac3DvT6Ziwu.jpg",
      "backdrop_path": "/qCsaZ2GoaCn5vmOUD9kCsyabr9o.jpg",
      "genre_ids": [
        18,
        80
      ],
      "vote_average": 6.978,
      "vote_count": 5244,
      "release_date": "2013-03-20"
    },
    {
      "id": 26963,
      "media_type": "movie",
      "title": "Таємниця абатства Келс",
      "original_title": "The Secret of Kells",
      "overview": "Ірландія, 9 століття. В абатстві Келс, яким керує настоятель Келах, живе маленький хлопчик на ім'я Брендан. Йому 12 років, і він разом з іншими ченцями старанно працює над зміцненням стін абатства для захисту від нападу норманів.  Одного дня в абатство приходить брат Ейдан, відомий майстер-ілюстратор та хранитель дивовижної книги з Іони. З цієї миті Брендану відкривається нове життя, сповнене пригод, в яких йому будуть допомагати нові друзі, кішка Пангур Бан і лісова фея Ешлінг.",
      "poster_path": "/vBymyj7QsXiW4TICD2JC5pAuBHO.jpg",
      "backdrop_path": "/740KCabjLKjsrxvEakmmJtDtAGY.jpg",
      "genre_ids": [
        16,
        10751,
        14
      ],
      "vote_average": 7.4,
      "vote_count": 797,
      "release_date": "2009-02-09"
    },
    {
      "id": 18032,
      "media_type": "movie",
      "title": "Таємниця Мунакра",
      "original_title": "The Secret of Moonacre",
      "overview": "Тринадцятирічній сирітці Марії доводиться залишити Лондон і переїхати до сера Бенджаміна, ексцентричного дядечка, якого вона раніше не знала, в його загадковий маєток \"Місячна Долина\". Марія опиняється у світі, розділеному стародавньою ворожнечею з темним родом де Нуар. Вона - остання Місячна принцеса, повинна подолати сімейну гордість і розкрити таємниці минулого. Але часу у неї лише до наступного повного місяця.",
      "poster_path": "/2zRrxXenmlujknCFVqdPNhitGB.jpg",
      "backdrop_path": "/wdpebYdOMtUJpfYZsUei07wOfuB.jpg",
      "genre_ids": [
        12,
        14,
        10749
      ],
      "vote_average": 6.587,
      "vote_count": 505,
      "release_date": "2009-02-06"
    }
  ]
}