{
  "slug": "slow-beauty",
  "icon": "<svg viewBox=\"0 0 512 512\" xmlns=\"http://www.w3.org/2000/svg\"><rect x=\"88\" y=\"96\" width=\"336\" height=\"320\" rx=\"16\" fill=\"none\" stroke=\"currentColor\" stroke-width=\"26\"/><g fill=\"currentColor\"><rect x=\"120\" y=\"128\" width=\"36\" height=\"36\" rx=\"6\"/><rect x=\"120\" y=\"238\" width=\"36\" height=\"36\" rx=\"6\"/><rect x=\"120\" y=\"348\" width=\"36\" height=\"36\" rx=\"6\"/><rect x=\"356\" y=\"128\" width=\"36\" height=\"36\" rx=\"6\"/><rect x=\"356\" y=\"238\" width=\"36\" height=\"36\" rx=\"6\"/><rect x=\"356\" y=\"348\" width=\"36\" height=\"36\" rx=\"6\"/></g></svg>",
  "title": "Естетика кадру",
  "lang": "uk",
  "updated_at": "2026-07-17T21:52:14Z",
  "items": [
    {
      "id": 56616,
      "media_type": "movie",
      "title": "不散",
      "original_title": "不散",
      "overview": "Темної дощової ночі в історичному кінотеатрі Тайбея демонструють останній фільм: стрічку 1967 року про бойові мистецтва «Готель „Брама дракона“».",
      "poster_path": "/bLCjXfMbFAHg6QvEmQSTjW6VzzN.jpg",
      "backdrop_path": "/lch9NDBb4oM0xKNEz0ZN7Mc27MS.jpg",
      "genre_ids": [
        18
      ],
      "vote_average": 6.786,
      "vote_count": 182,
      "release_date": "2003-12-12"
    },
    {
      "id": 253450,
      "media_type": "movie",
      "title": "Вбивця",
      "original_title": "刺客聶隱娘",
      "overview": "Китай, час правління династії Танг. Головна героїня - вбивця, яка закохалася в чоловіка, якого їй наказано вбити.",
      "poster_path": "/7cFx665GKJ9YZGgKW2UVXcsLw37.jpg",
      "backdrop_path": "/18J7JnWOb9UqfQZHrTCLPz4CeyO.jpg",
      "genre_ids": [
        18,
        28
      ],
      "vote_average": 6.382,
      "vote_count": 559,
      "release_date": "2015-08-27"
    },
    {
      "id": 486898,
      "media_type": "movie",
      "title": "Довгий день мандрує в ніч",
      "original_title": "地球最后的夜晚",
      "overview": "Ло Хунґву повертається в рідне місто на похорони батька. 12 років тому тут він мав роман із дівчиною друга, і відтоді вона поселилася в його спогадах, бажаннях і навіть кошмарах. Тепер для Хунґву в пошуках тієї жінки минуле змішується з реальністю, а реальність — із вигадкою.",
      "poster_path": "/zwMpjWTlTtoclGnQLe5hhCFYMQq.jpg",
      "backdrop_path": "/zJDaoc3HIHIgIOiY60NxqZUdXcp.jpg",
      "genre_ids": [
        18,
        9648
      ],
      "vote_average": 6.983,
      "vote_count": 286,
      "release_date": "2018-12-31"
    },
    {
      "id": 40751,
      "media_type": "movie",
      "title": "Прах часів",
      "original_title": "東邪西毒",
      "overview": "В центрі сюжету — Уянь Фень, який переїздить до Західної пустелі після того, як його залишає кохана жінка. Він займається тим, що винаймає вмілих воїнів для виконання замовних убивств. Хворобливе самолюбство робить його безжальним та цинічним, але по мірі того, як він знаходить друзів, знайомиться з клієнтами та майбутніми ворогами, він починає усвідомлювати ступінь своєї самотності…",
      "poster_path": "/jvLOKto7dBaIoqQpp5RnacaG4mA.jpg",
      "backdrop_path": "/smtzZRpE8hQkQNnhQg2TIRfcWcj.jpg",
      "genre_ids": [
        18,
        28
      ],
      "vote_average": 7.069,
      "vote_count": 400,
      "release_date": "1994-09-17"
    },
    {
      "id": 843,
      "media_type": "movie",
      "title": "Любовний настрій",
      "original_title": "花樣年華",
      "overview": "Гонконг, 1962 рік. Дві подружні пари, пан Чоу з дружиною і пані Су з чоловіком, одночасно поселяються в сусідніх квартирах. Поки їхні половинки пропадають на роботі чи в закордонних відрядженнях, Чоу і Су проводять багато часу на самоті і спілкуються одне з одним як звичайні сусіди. Все змінюється, коли вони дізнаються, що їхні партнери — коханці.",
      "poster_path": "/r2fYVKSlK3DKtdMbVxvIHHTfS2L.jpg",
      "backdrop_path": "/ffQFnAUm2Uu4RU0nijpjPRf9TBT.jpg",
      "genre_ids": [
        18,
        10749
      ],
      "vote_average": 8.087,
      "vote_count": 3297,
      "release_date": "2000-09-29"
    },
    {
      "id": 844,
      "media_type": "movie",
      "title": "2046",
      "original_title": "2046",
      "overview": "\"2046\" (сіквел фільму \"Любовний настрій\") — це візуально спокусливі марення зі спогадів і каяття, що проймають спритного коханця через досвід стосунків із шістьма жінками.  Головний герой Чоу змінює свій фах із картаря на письменника, а в усіх його зв'язках з красунями присутнє 2046. Як колоду перемішуючи минуле, сьогодення та майбутнє, 2046 — це, водночас, і готельний номер, в якому влаштовувала свої позашлюбні зустрічі пара з \"Любовного настрою\", і кінцева дата інтеграції Гонконга з Китаєм, і роман, який Чоу пише про таємничий поїзд, що прямує до місця під назвою \"2046\", знову і знову. Всі його пасажири жадають одного й того ж: відродити свої втрачені спогади. Кажуть, ніщо ніколи не змінюється в 2046. Ніхто не знає напевно, правда це чи ні, тому що всі, хто вирушав туди, вже ніколи не поверталися, окрім одного — Він був там, але Він вирішив повернутися. Він хотів змін...",
      "poster_path": "/dYx8z2Ui93BckzLpaWHarpX7MZG.jpg",
      "backdrop_path": "/h3JAMIeywbzobkhu2rt3mQAwRR1.jpg",
      "genre_ids": [
        18,
        878,
        10749
      ],
      "vote_average": 7.225,
      "vote_count": 1087,
      "release_date": "2004-09-29"
    },
    {
      "id": 290098,
      "media_type": "movie",
      "title": "Служниця",
      "original_title": "아가씨",
      "overview": "Двоє шахраїв працюють в тандемі: вона - краде, він - розводить людей. У них безумовно є талант, адже ніхто не виконує афери з такою чистотою і легкістю. Вони звикли до дрібних справ, обкрадаючи багатіїв з Токіо, але прийшов час взятися за щось велике. Дівчина йде працювати служницею в маєток, щоб втертися в довіру до заможної сім'ї...",
      "poster_path": "/gxRFfdvVgaK6uR85nQiOUgU3tIP.jpg",
      "backdrop_path": "/3upEZ0ltY7WwOSFVXrtiP34D48p.jpg",
      "genre_ids": [
        53,
        18,
        10749
      ],
      "vote_average": 8.185,
      "vote_count": 4382,
      "release_date": "2016-06-01"
    },
    {
      "id": 531428,
      "media_type": "movie",
      "title": "Портрет дівчини у вогні",
      "original_title": "Portrait de la jeune fille en feu",
      "overview": "Бретань, 1770 рік. Художниці Маріанн доручають зробити весільний портрет Елоїз — молодої жінки, яка щойно залишила монастир. Елоїз не надто прагне бути нареченою, а Маріанн не повинна казати їй про портрет. Вона спостерігає за нею вдень аби таємно малювати вночі.",
      "poster_path": "/zkckXGVJve80g0IcbL99PQGzC8M.jpg",
      "backdrop_path": "/ivJ5UzT6IzucLVfbZwCCwiJJoBz.jpg",
      "genre_ids": [
        18,
        10749
      ],
      "vote_average": 8.095,
      "vote_count": 2960,
      "release_date": "2019-09-06"
    },
    {
      "id": 600583,
      "media_type": "movie",
      "title": "У руках пса",
      "original_title": "The Power of the Dog",
      "overview": "Деспотичний, проте харизматичний фермер оголошує війну новій дружині брата та її сину-підлітку й знущається з них, доки назовні не виходить одна давня таємниця.",
      "poster_path": "/j1UuuZuEct0HgEl2U3QvWcflwz5.jpg",
      "backdrop_path": "/gAsHuCQMN7mv4uFIvM4ACQ09hPr.jpg",
      "genre_ids": [
        18,
        37
      ],
      "vote_average": 6.736,
      "vote_count": 2980,
      "release_date": "2021-10-25"
    }
  ]
}